airflow/providers/tesouro_gerencial/__init__.py
airflow/providers/tesouro_gerencial/provider.yaml
airflow/providers/tesouro_gerencial/example_dags/__init__.py
airflow/providers/tesouro_gerencial/example_dags/example_dag.py
airflow/providers/tesouro_gerencial/hooks/__init__.py
airflow/providers/tesouro_gerencial/hooks/tesouro_gerencial.py
airflow/providers/tesouro_gerencial/operators/__init__.py
airflow/providers/tesouro_gerencial/transfers/__init__.py
airflow/providers/tesouro_gerencial/transfers/relatorio_para_arquivo.py
airflow/providers/tesouro_gerencial/transfers/relatorio_para_mongo.py
airflow/providers/tesouro_gerencial/utils/__init__.py
airflow/providers/tesouro_gerencial/utils/excel.py
build/lib/airflow/providers/tesouro_gerencial/__init__.py
build/lib/airflow/providers/tesouro_gerencial/example_dags/__init__.py
build/lib/airflow/providers/tesouro_gerencial/example_dags/example_dag.py
build/lib/airflow/providers/tesouro_gerencial/hooks/__init__.py
build/lib/airflow/providers/tesouro_gerencial/hooks/tesouro_gerencial.py
build/lib/airflow/providers/tesouro_gerencial/operators/__init__.py
build/lib/airflow/providers/tesouro_gerencial/transfers/__init__.py
build/lib/airflow/providers/tesouro_gerencial/transfers/relatorio_para_arquivo.py
build/lib/airflow/providers/tesouro_gerencial/transfers/relatorio_para_mongo.py
build/lib/airflow/providers/tesouro_gerencial/utils/__init__.py
build/lib/airflow/providers/tesouro_gerencial/utils/excel.py
build/lib/build/lib/airflow/providers/tesouro_gerencial/__init__.py
build/lib/build/lib/airflow/providers/tesouro_gerencial/example_dags/__init__.py
build/lib/build/lib/airflow/providers/tesouro_gerencial/example_dags/example_dag.py
build/lib/build/lib/airflow/providers/tesouro_gerencial/hooks/__init__.py
build/lib/build/lib/airflow/providers/tesouro_gerencial/hooks/tesouro_gerencial.py
build/lib/build/lib/airflow/providers/tesouro_gerencial/operators/__init__.py
airflow_providers_tesouro_gerencial-1.3.0.dist-info/LICENSE.txt
airflow_providers_tesouro_gerencial-1.3.0.dist-info/METADATA
airflow_providers_tesouro_gerencial-1.3.0.dist-info/WHEEL
airflow_providers_tesouro_gerencial-1.3.0.dist-info/top_level.txt
airflow_providers_tesouro_gerencial-1.3.0.dist-info/RECORD
