Metadata-Version: 2.1
Name: airflow-providers-tesouro-gerencial
Version: 1.3.0
Summary: Provider do Airflow para comunicação com Tesouro Gerencial
Home-page: UNKNOWN
Author: Carlos Alberto Duarte Pinto
Author-email: carlos.adpinto@gmail.com
License: MIT
Project-URL: Homepage, https://tesourogerencial.tesouro.gov.br/
Project-URL: Source Code, https://github.com/CarlosAdp/airflow-providers-tesouro-gerencial
Keywords: airflow,tesouro,administracao,governo
Platform: UNKNOWN
Classifier: Environment :: Console
Classifier: Environment :: Web Environment
Classifier: Intended Audience :: Developers
Classifier: Intended Audience :: System Administrators
Classifier: Programming Language :: Python :: 3.8
Classifier: Programming Language :: Python :: 3.9
Classifier: Topic :: Office/Business :: Financial :: Accounting
Requires-Dist: apache-airflow
Requires-Dist: airflow-providers-siafi
Requires-Dist: requests
Requires-Dist: pandas
Requires-Dist: apache-airflow[mongo]
Requires-Dist: humanize
Requires-Dist: openpyxl
